Workbook

Sheet Read Me
A1: KTS Pre-Revenue SBA Readiness Workbook
A2: Built from the stated KTS circumstances. It is designed for a West Virginia SBDC / SBA funding-readiness conversation, not a loan application or financing promise.
A4: Current status | B4: Kidd’s Technical Services, LLC (KTS) is pre-revenue and bootstrapped.
A5: Customer evidence | B5: No signed customer contracts, deposits, invoices, purchase orders, or letters of intent are assumed at the start of this workbook.
A6: Business cash | B6: Starting KTS business-bank cash: $0.
A7: Funding cases | B7: Both $25,000 and $50,000 staged starter cases are included. Neither is approved financing.
A8: Founder pay | B8: Founder draw/payroll is $0 throughout this starter model. The $100,000 annual founder-pay goal remains a future target, not current payroll.
A9: Personal income | B9: Founder receives personal caregiver compensation through a Medicaid-waiver program. It is personal income, not KTS revenue, and is excluded from all KTS financial statements and repayment projections.
A10: Personal costs / debt | B10: User stated no personal living costs and no existing monthly debt. This workbook records that as user-provided information, but a lender/advisor may still ask for a private personal budget and supporting documentation.
A11: Business essentials | B11: KTS reported no existing business equipment, software, domains, phone, internet, insurance, or website. Funding cases therefore include startup provisions for essentials.
A12: Revenue focus | B12: Initial sales focus: local-business packages. Revenue projections are assumptions only, not booked sales.
A13: ALLIS boundary | B13: ALLIS revenue is $0 in every month and excluded from funding, repayment, staffing, and revenue assumptions until market-ready and separately authorized.
A14: Legal planning | B14: Proposed, not contracted: $150/hour; up to 33 hours per quarter; $4,950 quarterly legal budget; $50 quarterly minor operating-overhead reserve; $20,000 annual planning total.
A17: Use guidance | B17: Edit only yellow input cells after you have a quote, real pipeline evidence, actual bank balance, or lender term. Keep private owner records, caregiver-income documents, tax records, and bank statements outside public GitHub.

Sheet Assumptions
A1: Assumptions
A2: Yellow fields are editable. Every item is classified so planning values are not mistaken for verified facts.
A4: Area | B4: Input | C4: Value | D4: Unit | E4: Classification | F4: Evidence / source | G4: How to use it | H4: Public-safe?
A5: Model | B5: Start month | C5: 46266 | D5: Month | E5: User-confirmed | F5: Conversation | G5: Change only if start changes | H5: Yes
A6: Cash | B6: Starting KTS business cash | C6: 0 | D6: USD | E6: User-confirmed | F6: Conversation | G6: Use actual KTS bank balance; currently $0 | H6: Yes
A7: Funding | B7: Discussion case A | C7: 25000 | D7: USD | E7: User-confirmed choice | F7: Conversation | G7: Not approved financing | H7: Yes
A8: Funding | B8: Discussion case B | C8: 50000 | D8: USD | E8: User-confirmed choice | F8: Conversation | G8: Not approved financing | H8: Yes
A9: Revenue | B9: Contracts / deposits / invoices / POs / LOIs at start | C9: 0 | D9: USD | E9: User-confirmed | F9: Conversation | G9: Do not assume any customer cash | H9: Yes
A10: Revenue | B10: ALLIS revenue | C10: 0 | D10: USD | E10: Business boundary | F10: KTS planning position | G10: Always $0 in starter model | H10: Yes
A11: People | B11: Founder payroll, Months 1–24 | C11: 0 | D11: USD/month | E11: User-confirmed | F11: Conversation | G11: No salary assumed in starter model | H11: Yes
A12: People | B12: Founder future annual target | C12: 100000 | D12: USD/year | E12: Stated target | F12: Conversation | G12: Future target only; do not use for repayment | H12: Yes
A13: Personal | B13: Medicaid-waiver caregiver compensation | C13: Excluded | D13: Personal income | E13: User-confirmed | F13: Private pay/tax documents | G13: Not KTS revenue or cash flow; disclose privately if requested | H13: No
A14: Personal | B14: Personal living costs | C14: 0 | D14: USD/month | E14: User-provided | F14: Conversation | G14: Validate privately with advisor/lender if requested | H14: No
A15: Personal | B15: Existing monthly debt payments | C15: 0 | D15: USD/month | E15: User-provided | F15: Conversation | G15: Validate privately with advisor/lender if requested | H15: No
A16: Assets | B16: Existing KTS equipment/software/website/insurance | C16: 0 | D16: USD | E16: User-confirmed | F16: Conversation | G16: Fund startup essentials from case A or B | H16: Yes
A17: Sales | B17: Initial revenue focus | C17: Local-business packages | D17: Text | E17: User-confirmed | F17: Conversation | G17: Only initial modeled service line | H17: Yes
A18: Sales | B18: Average local-business package price | C18: 2500 | D18: USD | E18: Planning assumption | F18: Replace with actual offers and quotes | G18: Editable assumption | H18: Yes
A19: Sales | B19: Deposit percentage | C19: 0.5 | D19: Percent | E19: Planning policy | F19: Future agreements | G19: 50% before delivery; edit only if terms change | H19: Yes
A20: Sales | B20: Final collection delay | C20: 30 | D20: Days | E20: Planning assumption | F20: Future agreements | G20: Illustrative; not guaranteed collection | H20: Yes
A21: Sales | B21: Direct project cost ratio | C21: 0.3 | D21: Percent | E21: Planning assumption | F21: Actual job-costing data | G21: Contractors/project expenses only | H21: Yes
A22: Legal | B22: Proposed hourly rate | C22: 150 | D22: USD/hour | E22: Proposed, not contracted | F22: Conversation | G22: Obtain signed engagement terms if accepted | H22: Yes
A23: Legal | B23: Proposed hours per quarter | C23: 33 | D23: Hours | E23: Proposed, not contracted | F23: Conversation | G23: Cap per quarter | H23: Yes
A24: Legal | B24: Quarterly legal budget | C24: 4950 | D24: USD | E24: Calculated planning budget | F24: 33 × $150 | G24: Actual invoices govern | H24: Yes
A25: Legal | B25: Quarterly minor-overhead reserve | C25: 50 | D25: USD | E25: Planning assumption | F25: Conversation | G25: Mileage, parking, postage, supplies, etc. | H25: Yes
A26: Ops | B26: Software/domains/storage/communications | C26: 250 | D26: USD/month | E26: Planning assumption | F26: Vendor quotes needed | G26: Startup allowance | H26: Yes
A27: Ops | B27: Insurance | C27: 250 | D27: USD/month | E27: Planning assumption | F27: Insurance quotes needed | G27: Startup allowance | H27: Yes
A28: Ops | B28: Bookkeeping/accounting | C28: 150 | D28: USD/month | E28: Planning assumption | F28: Provider quote needed | G28: Startup allowance | H28: Yes
A29: Ops | B29: Marketing/outreach | C29: 500 | D29: USD/month | E29: Planning assumption | F29: Marketing plan needed | G29: Startup allowance | H29: Yes
... A33: Debt | B33: Illustrative loan term | C33: 84 | D33: Months | E33: Illustrative only | F33: Lender quote needed | G33: Never present as approved term | H33: Yes

Sheet Funding Cases
A1: Funding Cases
A2: Use-of-funds discussion cases. $25,000 and $50,000 totals reconcile exactly. Actual financing must follow lender and advisor review.
A4: Use of funds | B4: $25,000 case | C4: $50,000 case | D4: Why it is needed | E4: Evidence to obtain | F4: Spending control | G4: Notes
A5: Formation, legal, and professional reserve | B5: 2500 | C5: 5000 | D5: Entity setup, contracts, legal questions, professional setup | E5: Written scope/quote where available | F5: Pay only documented invoices/approved costs | G5: Legal relationship remains proposed, not contracted
A6: Insurance and compliance | B6: 2500 | C6: 5000 | D6: Required coverage and launch compliance | E6: Insurance quotes | F6: Bind/pay only selected policy | G6: Replace estimates with quote
A7: Core software, domains, email, storage, communications | B7: 2500 | C7: 6000 | D7: Business email, domain, backup, collaboration, mapping/tools | E7: Vendor pricing | F7: Monthly spending cap | G7: No existing stack reported
A8: Equipment and field tools | B8: 4000 | C8: 8000 | D8: Laptop/workstation, peripherals, storage, basic field tools | E8: Written equipment quotes | F8: Buy only necessary durable tools | G8: No existing business equipment reported
A9: Website, portfolio, outreach, proposals, local sales | B9: 3500 | C9: 8000 | D9: Customer acquisition and credible service presentation | E9: Marketing and vendor estimates | F9: Track inquiries, proposals, wins, collections | G9: Initial focus: local-business packages
A10: Initial operating reserve | B10: 7000 | C10: 10000 | D10: Cash cushion while selling and collecting deposits | E10: 24-month cash flow | F10: Monthly budget review | G10: No founder payroll assumed
A11: Project delivery / contractor reserve | B11: 2500 | C11: 6000 | D11: Direct delivery costs for paid customer projects | E11: Signed scope + deposit or funding | F11: Release only for funded work | G11: No standing contractor commitment
A12: Contingency | B12: 500 | C12: 2000 | D12: Unexpected documented startup/delivery need | E12: Documented need | F12: Owner approval / receipt | G12: Not discretionary compensation
A13: Total | B13: =SUM(B5:B12) | C13: =SUM(C5:C12)

Sheet Local Business Sales
A1: Local-Business Sales Ramp
A2: This is an editable conservative sales-planning ramp. It is not booked revenue. All revenue must be replaced with real leads, signed scopes, deposits, invoices, and collections.
A4: Sales line | B4: Sep-26 | C4: Oct-26 | D4: Nov-26 | E4: Dec-26 | F4: Jan-27 | G4: Feb-27 | H4: Mar-27 | I4: Apr-27 | J4: May-27 | K4: Jun-27 | L4: Jul-27 | M4: Aug-27 | N4: Sep-27 | O4: Oct-27 | P4: Nov-27 | Q4: Dec-27 | R4: Jan-28 | S4: Feb-28 | T4: Mar-28 | U4: Apr-28 | V4: May-28 | W4: Jun-28 | X4: Jul-28 | Y4: Aug-28
A5: Planned packages sold | B5: 0 | C5: 0 | D5: 0 | E5: 1 | F5: 1 | G5: 1 | H5: 2 | I5: 2 | J5: 2 | K5: 2 | L5: 2 | M5: 2 | N5: 3 | O5: 3 | P5: 3 | Q5: 3 | R5: 3 | S5: 3 | T5: 4 | U5: 4 | V5: 4 | W5: 4 | X5: 4 | Y5: 4
A6: Average price per package | B6: =Assumptions!$C$18 | C6: =Assumptions!$C$18 | D6: =Assumptions!$C$18 | E6: =Assumptions!$C$18 | F6: =Assumptions!$C$18 | G6: =Assumptions!$C$18 | H6: =Assumptions!$C$18 | I6: =Assumptions!$C$18 | ... Y6: =Assumptions!$C$18
A7: Gross booked sales | B7: =B5*B6 | C7: =C5*C6 | D7: =D5*D6 | E7: =E5*E6 | F7: =F5*F6 | G7: =G5*G6 | H7: =H5*H6 | I7: =I5*I6 | ... Y7: =Y5*Y6
A8: Deposit cash collected | B8: =B7*Assumptions!$C$19 | C8: =C7*Assumptions!$C$19 | D8: =D7*Assumptions!$C$19 | E8: =E7*Assumptions!$C$19 | F8: =F7*Assumptions!$C$19 | G8: =G7*Assumptions!$C$19 | H8: =H7*Assumptions!$C$19 | I8: =I7*Assumptions!$C$19 | ... Y8: =Y7*Assumptions!$C$19
A9: Final cash collected from prior packages | B9: 0 | C9: =B7*(1-Assumptions!$C$19) | D9: =C7*(1-Assumptions!$C$19) | E9: =D7*(1-Assumptions!$C$19) | F9: =E7*(1-Assumptions!$C$19) | G9: =F7*(1-Assumptions!$C$19) | H9: =G7*(1-Assumptions!$C$19) | I9: =H7*(1-Assumptions!$C$19) | J9: =I7*(1-Assumptions!$C$19) | ... Y9: =X7*(1-Assumptions!$C$19)
A10: Total customer cash collected | B10: =B8+B9 | C10: =C8+C9 | D10: =D8+D9 | E10: =E8+E9 | F10: =F8+F9 | G10: =G8+G9 | H10: =H8+H9 | I10: =I8+I9 | ... Y10: =Y8+Y9
A11: Direct project cost | B11: =B10*Assumptions!$C$21 | C11: =C10*Assumptions!$C$21 | D11: =D10*Assumptions!$C$21 | E11: =E10*Assumptions!$C$21 | F11: =F10*Assumptions!$C$21 | G11: =G10*Assumptions!$C$21 | H11: =H10*Assumptions!$C$21 | I11: =I10*Assumptions!$C$21 | ... Y11: =Y10*Assumptions!$C$21
A12: Gross contribution before operating costs | B12: =B10-B11 | C12: =C10-C11 | D12: =D10-D11 | E12: =E10-E11 | F12: =F10-F11 | G12: =G10-G11 | H12: =H10-H11 | I12: =I10-I11 | ... Y12: =Y10-Y11
A13: Evidence status | B13: Planning assumption—replace with pipeline evidence | C13: Planning assumption—replace with pipeline evidence | D13: Planning assumption—replace with pipeline evidence | E13: Planning assumption—replace with pipeline evidence | F13: Planning assumption—replace with pipeline evidence | G13: Planning assumption—replace with pipeline evidence | H13: Planning assumption—replace with pipeline evidence | I13: Planning assumption—replace with pipeline evidence | J13: Planning assumption—replace with pipeline evidence | K13: Planning assumption—replace with pipeline evidence | L13: Planning assumption—replace with pipeline evidence | M13: Planning assumption—replace with pipeline evidence | N13: Planning assumption—replace with pipeline evidence | O13: Planning assumption—replace with pipeline evidence | P13: Planning assumption—replace with pipeline evidence | Q13: Planning assumption—replace with pipeline evidence | R13: Planning assumption—replace with pipeline evidence | S13: Planning assumption—replace with pipeline evidence | T13: Planning assumption—replace with pipeline evidence | U13: Planning assumption—replace with pipeline evidence | V13: Planning assumption—replace with pipeline evidence | W13: Planning assumption—replace with pipeline evidence | X13: Planning assumption—replace with pipeline evidence | Y13: Planning assumption—replace with pipeline evidence

Sheet Cash Flow $25k
A1: Cash Flow $25k
A2: Pre-revenue, local-business-package starter scenario. Loan proceeds are illustrative only. Customer cash comes solely from the Local-Business Sales Ramp planning assumptions.
A4: Cash-flow line | B4: Sep-26 | C4: Oct-26 | D4: Nov-26 | E4: Dec-26 | F4: Jan-27 | G4: Feb-27 | H4: Mar-27 | I4: Apr-27 | J4: May-27 | K4: Jun-27 | L4: Jul-27 | M4: Aug-27 | N4: Sep-27 | O4: Oct-27 | P4: Nov-27 | Q4: Dec-27 | R4: Jan-28 | S4: Feb-28 | T4: Mar-28 | U4: Apr-28 | V4: May-28 | W4: Jun-28 | X4: Jul-28 | Y4: Aug-28
A5: Beginning cash | B5: =Assumptions!$C$6 | C5: =B24 | D5: =C24 | E5: =D24 | F5: =E24 | G5: =F24 | H5: =G24 | I5: =H24 | J5: =I24 | ... Y5: =X24
A6: Illustrative funding proceeds | B6: 25000 | C6: 0 | D6: 0 | E6: 0 | F6: 0 | G6: 0 | H6: 0 | I6: 0 | J6: 0 | K6: 0 | L6: 0 | M6: 0 | N6: 0 | O6: 0 | P6: 0 | Q6: 0 | R6: 0 | S6: 0 | T6: 0 | U6: 0 | V6: 0 | W6: 0 | X6: 0 | Y6: 0
A7: Owner contribution | B7: 0 | C7: 0 | D7: 0 | E7: 0 | F7: 0 | G7: 0 | H7: 0 | I7: 0 | J7: 0 | K7: 0 | L7: 0 | M7: 0 | N7: 0 | O7: 0 | P7: 0 | Q7: 0 | R7: 0 | S7: 0 | T7: 0 | U7: 0 | V7: 0 | W7: 0 | X7: 0 | Y7: 0
A8: Customer deposits collected | B8: ='Local Business Sales'!B8 | C8: ='Local Business Sales'!C8 | D8: ='Local Business Sales'!D8 | E8: ='Local Business Sales'!E8 | F8: ='Local Business Sales'!F8 | G8: ='Local Business Sales'!G8 | H8: ='Local Business Sales'!H8 | I8: ='Local Business Sales'!I8 | ... Y8: ='Local Business Sales'!Y8
A9: Customer final collections | B9: ='Local Business Sales'!B9 | C9: ='Local Business Sales'!C9 | D9: ='Local Business Sales'!D9 | E9: ='Local Business Sales'!E9 | F9: ='Local Business Sales'!F9 | G9: ='Local Business Sales'!G9 | H9: ='Local Business Sales'!H9 | I9: ='Local Business Sales'!I9 | ... Y9: ='Local Business Sales'!Y9
A10: Total cash inflows | B10: =SUM(B6:B9) | C10: =SUM(C6:C9) | D10: =SUM(D6:D9) | E10: =SUM(E6:E9) | F10: =SUM(F6:F9) | G10: =SUM(G6:G9) | H10: =SUM(H6:H9) | I10: =SUM(I6:I9) | ... Y10: =SUM(Y6:Y9)
A11: Direct project costs | B11: ='Local Business Sales'!B11 | C11: ='Local Business Sales'!C11 | D11: ='Local Business Sales'!D11 | E11: ='Local Business Sales'!E11 | F11: ='Local Business Sales'!F11 | G11: ='Local Business Sales'!G11 | H11: ='Local Business Sales'!H11 | I11: ='Local Business Sales'!I11 | ... Y11: ='Local Business Sales'!Y11
A12: Founder payroll | B12: 0 | C12: 0 | D12: 0 | E12: 0 | F12: 0 | G12: 0 | H12: 0 | I12: 0 | J12: 0 | K12: 0 | L12: 0 | M12: 0 | N12: 0 | O12: 0 | P12: 0 | Q12: 0 | R12: 0 | S12: 0 | T12: 0 | U12: 0 | V12: 0 | W12: 0 | X12: 0 | Y12: 0
A13: Legal services | B13: =Assumptions!$C$24 | C13: 0 | D13: 0 | E13: =Assumptions!$C$24 | F13: 0 | G13: 0 | H13: =Assumptions!$C$24 | I13: 0 | J13: 0 | K13: =Assumptions!$C$24 | L13: 0 | M13: 0 | N13: =Assumptions!$C$24 | O13: 0 | P13: 0 | Q13: =Assumptions!$C$24 | R13: 0 | S13: 0 | T13: =Assumptions!$C$24 | U13: 0 | V13: 0 | W13: =Assumptions!$C$24 | X13: 0 | Y13: 0
A14: Minor operating overhead | B14: =Assumptions!$C$25 | C14: 0 | D14: 0 | E14: =Assumptions!$C$25 | F14: 0 | G14: 0 | H14: =Assumptions!$C$25 | I14: 0 | J14: 0 | K14: =Assumptions!$C$25 | L14: 0 | M14: 0 | N14: =Assumptions!$C$25 | O14: 0 | P14: 0 | Q14: =Assumptions!$C$25 | R14: 0 | S14: 0 | T14: =Assumptions!$C$25 | U14: 0 | V14: 0 | W14: =Assumptions!$C$25 | X14: 0 | Y14: 0
A15: Software/domains/storage/communications | B15: =Assumptions!$C$26 | C15: =Assumptions!$C$26 | D15: =Assumptions!$C$26 | E15: =Assumptions!$C$26 | F15: =Assumptions!$C$26 | G15: =Assumptions!$C$26 | H15: =Assumptions!$C$26 | I15: =Assumptions!$C$26 | ... Y15: =Assumptions!$C$26
A16: Insurance | B16: =Assumptions!$C$27 | C16: =Assumptions!$C$27 | D16: =Assumptions!$C$27 | E16: =Assumptions!$C$27 | F16: =Assumptions!$C$27 | G16: =Assumptions!$C$27 | H16: =Assumptions!$C$27 | I16: =Assumptions!$C$27 | ... Y16: =Assumptions!$C$27
A17: Bookkeeping/accounting | B17: =Assumptions!$C$28 | C17: =Assumptions!$C$28 | D17: =Assumptions!$C$28 | E17: =Assumptions!$C$28 | F17: =Assumptions!$C$28 | G17: =Assumptions!$C$28 | H17: =Assumptions!$C$28 | I17: =Assumptions!$C$28 | ... Y17: =Assumptions!$C$28
A18: Marketing/outreach | B18: =Assumptions!$C$29 | C18: =Assumptions!$C$29 | D18: =Assumptions!$C$29 | E18: =Assumptions!$C$29 | F18: =Assumptions!$C$29 | G18: =Assumptions!$C$29 | H18: =Assumptions!$C$29 | I18: =Assumptions!$C$29 | ... Y18: =Assumptions!$C$29
A19: General operations | B19: =Assumptions!$C$30 | C19: 0 | D19: 0 | E19: 0 | F19: 0 | G19: 0 | H19: 0 | I19: 0 | J19: 0 | K19: 0 | L19: 0 | M19: 0 | N19: 0 | O19: 0 | P19: 0 | Q19: 0 | R19: 0 | S19: 0 | T19: 0 | U19: 0 | V19: 0 | W19: 0 | X19: 0 | Y19: 0
A20: Equipment/startup setup | B20: 0 | C20: 0 | D20: 0 | E20: =IFERROR(-PMT(Assumptions!$C$31/12,Assumptions!$C$32,25000),0) | F20: =IFERROR(-PMT(Assumptions!$C$31/12,Assumptions!$C$32,25000),0) | G20: =IFERROR(-PMT(Assumptions!$C$31/12,Assumptions!$C$32,25000),0) | H20: =IFERROR(-PMT(Assumptions!$C$31/12,Assumptions!$C$32,25000),0) | I20: =IFERROR(-PMT(Assumptions!$C$31/12,Assumptions!$C$32,25000),0) | J20: =IFERROR(-PMT(Assumptions!$C$31/12,Assumptions!$C$32,25000),0) | K20: =IFERROR(-PMT(Assumptions!$C$31/12,Assumptions!$C$32,25000),0) | L20: =IFERROR(-PMT(Assumptions!$C$31/12,Assumptions!$C$32,25000),0) | ... Y20: =IFERROR(-PMT(Assumptions!$C$31/12,Assumptions!$C$32,25000),0)
A21: Estimated loan payment | B21: =SUM(B11:B20) | C21: =SUM(C11:C20) | D21: =SUM(D11:D20) | E21: =SUM(E11:E20) | F21: =SUM(F11:F20) | G21: =SUM(G11:G20) | H21: =SUM(H11:H20) | I21: =SUM(I11:I20) | ... Y21: =SUM(Y11:Y20)
A22: Total cash outflows | B22: =B10-B21 | C22: =C10-C21 | D22: =D10-D21 | E22: =E10-E21 | F22: =F10-F21 | G22: =G10-G21 | H22: =H10-H21 | I22: =I10-I21 | ... Y22: =Y10-Y21
A23: Net cash movement | B23: =B5+B22 | C23: =C5+C22 | D23: =D5+D22 | E23: =E5+E22 | F23: =F5+F22 | G23: =G5+G22 | H23: =H5+H22 | I23: =I5+I22 | ... Y23: =Y5+Y22
A24: Ending cash

Sheet Cash Flow $50k
A1: Cash Flow $50k
A2: Pre-revenue, local-business-package starter scenario. Loan proceeds are illustrative only. Customer cash comes solely from the Local-Business Sales Ramp planning assumptions.
A4: Cash-flow line | B4: Sep-26 | C4: Oct-26 | D4: Nov-26 | E4: Dec-26 | F4: Jan-27 | G4: Feb-27 | H4: Mar-27 | I4: Apr-27 | J4: May-27 | K4: Jun-27 | L4: Jul-27 | M4: Aug-27 | N4: Sep-27 | O4: Oct-27 | P4: Nov-27 | Q4: Dec-27 | R4: Jan-28 | S4: Feb-28 | T4: Mar-28 | U4: Apr-28 | V4: May-28 | W4: Jun-28 | X4: Jul-28 | Y4: Aug-28
A5: Beginning cash | B5: =Assumptions!$C$6 | C5: =B24 | D5: =C24 | E5: =D24 | F5: =E24 | G5: =F24 | H5: =G24 | I5: =H24 | J5: =I24 | ... Y5: =X24
A6: Illustrative funding proceeds | B6: 50000 | C6: 0 | D6: 0 | E6: 0 | F6: 0 | G6: 0 | H6: 0 | I6: 0 | J6: 0 | K6: 0 | L6: 0 | M6: 0 | N6: 0 | O6: 0 | P6: 0 | Q6: 0 | R6: 0 | S6: 0 | T6: 0 | U6: 0 | V6: 0 | W6: 0 | X6: 0 | Y6: 0
A7: Owner contribution | B7: 0 | C7: 0 | D7: 0 | E7: 0 | F7: 0 | G7: 0 | H7: 0 | I7: 0 | J7: 0 | K7: 0 | L7: 0 | M7: 0 | N7: 0 | O7: 0 | P7: 0 | Q7: 0 | R7: 0 | S7: 0 | T7: 0 | U7: 0 | V7: 0 | W7: 0 | X7: 0 | Y7: 0
A8: Customer deposits collected | B8: ='Local Business Sales'!B8 | C8: ='Local Business Sales'!C8 | D8: ='Local Business Sales'!D8 | E8: ='Local Business Sales'!E8 | F8: ='Local Business Sales'!F8 | G8: ='Local Business Sales'!G8 | H8: ='Local Business Sales'!H8 | I8: ='Local Business Sales'!I8 | ... Y8: ='Local Business Sales'!Y8
A9: Customer final collections | B9: ='Local Business Sales'!B9 | C9: ='Local Business Sales'!C9 | D9: ='Local Business Sales'!D9 | E9: ='Local Business Sales'!E9 | F9: ='Local Business Sales'!F9 | G9: ='Local Business Sales'!G9 | H9: ='Local Business Sales'!H9 | I9: ='Local Business Sales'!I9 | ... Y9: ='Local Business Sales'!Y9
A10: Total cash inflows | B10: =SUM(B6:B9) | C10: =SUM(C6:C9) | D10: =SUM(D6:D9) | E10: =SUM(E6:E9) | F10: =SUM(F6:F9) | G10: =SUM(G6:G9) | H10: =SUM(H6:H9) | I10: =SUM(I6:I9) | ... Y10: =SUM(Y6:Y9)
A11: Direct project costs | B11: ='Local Business Sales'!B11 | C11: ='Local Business Sales'!C11 | D11: ='Local Business Sales'!D11 | E11: ='Local Business Sales'!E11 | F11: ='Local Business Sales'!F11 | G11: ='Local Business Sales'!G11 | H11: ='Local Business Sales'!H11 | I11: ='Local Business Sales'!I11 | ... Y11: ='Local Business Sales'!Y11
A12: Founder payroll | B12: 0 | C12: 0 | D12: 0 | E12: 0 | F12: 0 | G12: 0 | H12: 0 | I12: 0 | J12: 0 | K12: 0 | L12: 0 | M12: 0 | N12: 0 | O12: 0 | P12: 0 | Q12: 0 | R12: 0 | S12: 0 | T12: 0 | U12: 0 | V12: 0 | W12: 0 | X12: 0 | Y12: 0
A13: Legal services | B13: =Assumptions!$C$24 | C13: 0 | D13: 0 | E13: =Assumptions!$C$24 | F13: 0 | G13: 0 | H13: =Assumptions!$C$24 | I13: 0 | J13: 0 | K13: =Assumptions!$C$24 | L13: 0 | M13: 0 | N13: =Assumptions!$C$24 | O13: 0 | P13: 0 | Q13: =Assumptions!$C$24 | R13: 0 | S13: 0 | T13: =Assumptions!$C$24 | U13: 0 | V13: 0 | W13: =Assumptions!$C$24 | X13: 0 | Y13: 0
A14: Minor operating overhead | B14: =Assumptions!$C$25 | C14: 0 | D14: 0 | E14: =Assumptions!$C$25 | F14: 0 | G14: 0 | H14: =Assumptions!$C$25 | I14: 0 | J14: 0 | K14: =Assumptions!$C$25 | L14: 0 | M14: 0 | N14: =Assumptions!$C$25 | O14: 0 | P14: 0 | Q14: =Assumptions!$C$25 | R14: 0 | S14: 0 | T14: =Assumptions!$C$25 | U14: 0 | V14: 0 | W14: =Assumptions!$C$25 | X14: 0 | Y14: 0
A15: Software/domains/storage/communications | B15: =Assumptions!$C$26 | C15: =Assumptions!$C$26 | D15: =Assumptions!$C$26 | E15: =Assumptions!$C$26 | F15: =Assumptions!$C$26 | G15: =Assumptions!$C$26 | H15: =Assumptions!$C$26 | I15: =Assumptions!$C$26 | ... Y15: =Assumptions!$C$26
A16: Insurance | B16: =Assumptions!$C$27 | C16: =Assumptions!$C$27 | D16: =Assumptions!$C$27 | E16: =Assumptions!$C$27 | F16: =Assumptions!$C$27 | G16: =Assumptions!$C$27 | H16: =Assumptions!$C$27 | I16: =Assumptions!$C$27 | ... Y16: =Assumptions!$C$27
A17: Bookkeeping/accounting | B17: =Assumptions!$C$28 | C17: =Assumptions!$C$28 | D17: =Assumptions!$C$28 | E17: =Assumptions!$C$28 | F17: =Assumptions!$C$28 | G17: =Assumptions!$C$28 | H17: =Assumptions!$C$28 | I17: =Assumptions!$C$28 | ... Y17: =Assumptions!$C$28
A18: Marketing/outreach | B18: =Assumptions!$C$29 | C18: =Assumptions!$C$29 | D18: =Assumptions!$C$29 | E18: =Assumptions!$C$29 | F18: =Assumptions!$C$29 | G18: =Assumptions!$C$29 | H18: =Assumptions!$C$29 | I18: =Assumptions!$C$29 | ... Y18: =Assumptions!$C$29
A19: General operations | B19: =Assumptions!$C$30 | C19: 0 | D19: 0 | E19: 0 | F19: 0 | G19: 0 | H19: 0 | I19: 0 | J19: 0 | K19: 0 | L19: 0 | M19: 0 | N19: 0 | O19: 0 | P19: 0 | Q19: 0 | R19: 0 | S19: 0 | T19: 0 | U19: 0 | V19: 0 | W19: 0 | X19: 0 | Y19: 0
A20: Equipment/startup setup | B20: 0 | C20: 0 | D20: 0 | E20: =IFERROR(-PMT(Assumptions!$C$31/12,Assumptions!$C$32,50000),0) | F20: =IFERROR(-PMT(Assumptions!$C$31/12,Assumptions!$C$32,50000),0) | G20: =IFERROR(-PMT(Assumptions!$C$31/12,Assumptions!$C$32,50000),0) | H20: =IFERROR(-PMT(Assumptions!$C$31/12,Assumptions!$C$32,50000),0) | I20: =IFERROR(-PMT(Assumptions!$C$31/12,Assumptions!$C$32,50000),0) | J20: =IFERROR(-PMT(Assumptions!$C$31/12,Assumptions!$C$32,50000),0) | K20: =IFERROR(-PMT(Assumptions!$C$31/12,Assumptions!$C$32,50000),0) | L20: =IFERROR(-PMT(Assumptions!$C$31/12,Assumptions!$C$32,50000),0) | ... Y20: =IFERROR(-PMT(Assumptions!$C$31/12,Assumptions!$C$32,50000),0)
A21: Estimated loan payment | B21: =SUM(B11:B20) | C21: =SUM(C11:C20) | D21: =SUM(D11:D20) | E21: =SUM(E11:E20) | F21: =SUM(F11:F20) | G21: =SUM(G11:G20) | H21: =SUM(H11:H20) | I21: =SUM(I11:I20) | ... Y21: =SUM(Y11:Y20)
A22: Total cash outflows | B22: =B10-B21 | C22: =C10-C21 | D22: =D10-D21 | E22: =E10-E21 | F22: =F10-F21 | G22: =G10-G21 | H22: =H10-H21 | I22: =I10-I21 | ... Y22: =Y10-Y21
A23: Net cash movement | B23: =B5+B22 | C23: =C5+C22 | D23: =D5+D22 | E23: =E5+E22 | F23: =F5+F22 | G23: =G5+G22 | H23: =H5+H22 | I23: =I5+I22 | ... Y23: =Y5+Y22
A24: Ending cash

Sheet Pipeline Tracker
A1: Pipeline Tracker
A2: Starts empty because KTS has no current customer commitments. Add records as they occur; never convert informal interest into revenue.
A4: Lead / customer | B4: Service | C4: Stage | D4: Quoted value | E4: Deposit % | F4: Expected close month | G4: Deposit received? | H4: Final received? | I4: Evidence / next action | J4: Direct cost estimate | K4: Notes
D5: 0 | E5: 0.5 | J5: 0
D6: 0 | E6: 0.5 | J6: 0
D7: 0 | E7: 0.5 | J7: 0
D8: 0 | E8: 0.5 | J8: 0
D9: 0 | E9: 0.5 | J9: 0
D10: 0 | E10: 0.5 | J10: 0
D11: 0 | E11: 0.5 | J11: 0
D12: 0 | E12: 0.5 | J12: 0
D13: 0 | E13: 0.5 | J13: 0
D14: 0 | E14: 0.5 | J14: 0
D15: 0 | E15: 0.5 | J15: 0
D16: 0 | E16: 0.5 | J16: 0
... D34: 0 | E34: 0.5 | J34: 0

Sheet Debt Scenarios
A1: Debt Scenarios
A2: These are purely illustrative mathematical scenarios using editable assumptions. They are not an SBA rate, lender quote, qualification, or approval.
A4: Funding case | B4: Loan amount | C4: Annual rate | D4: Term months | E4: Estimated monthly payment | F4: Estimated annual debt service | G4: Source / warning
A5: Starter A | B5: 25000 | C5: 0.11 | D5: 84 | E5: =IFERROR(-PMT(C5/12,D5,B5),0) | F5: =E5*12 | G5: Illustrative—replace with lender terms.
A6: Starter B | B6: 50000 | C6: 0.11 | D6: 84 | E6: =IFERROR(-PMT(C6/12,D6,B6),0) | F6: =E6*12 | G6: Illustrative—replace with lender terms.
A7: Alternative $50k / 5 years | B7: 50000 | C7: 0.13 | D7: 60 | E7: =IFERROR(-PMT(C7/12,D7,B7),0) | F7: =E7*12 | G7: Illustrative—replace with lender terms.
A8: Alternative $50k / 10 years | B8: 50000 | C8: 0.09 | D8: 120 | E8: =IFERROR(-PMT(C8/12,D8,B8),0) | F8: =E8*12 | G8: Illustrative—replace with lender terms.

Sheet Assumptions Register
A1: Assumptions Register
A2: Bring this to the WVSBDC meeting so assumptions can be replaced with evidence rather than treated as facts.
A4: Topic | B4: Current treatment | C4: Status | D4: Evidence needed | E4: What not to claim | F4: Next action
A5: KTS revenue | B5: No current revenue | C5: Verified current condition | D5: Business records / pipeline | E5: Do not claim bookings, backlog, or collections | F5: Build prospect and proposal record
A6: Customer proof | B6: No contracts, deposits, invoices, POs, or LOIs | C6: Verified current condition | D6: Future signed scopes/deposits | E6: Do not imply commitments | F6: Conduct discovery; send real proposals
A7: Funding | B7: $25k and $50k discussion cases | C7: Planning cases only | D7: SBDC/lender feedback | E7: Do not claim approval | F7: Ask which case is appropriate
A8: Local-business sales ramp | B8: Units and price assumptions in workbook | C8: Planning assumptions | D8: Quotes, proposals, deposits, invoices | E8: Do not call forecast revenue | F8: Update monthly
A9: ALLIS | B9: $0 revenue | C9: Business boundary | D9: Future market authorization | E9: Do not use as repayment source | F9: Keep excluded
A10: Founder compensation | B10: $0 in starter model; $100k future target | C10: User-confirmed / target | D10: Future cash trigger and payroll setup | E10: Do not claim current payroll | F10: Keep deferred
A11: Caregiver payment | B11: Personal Medicaid-waiver income | C11: User-confirmed personal context | D11: Private payment/tax records if requested | E11: Do not list as KTS revenue | F11: Discuss privately with advisor
A12: Legal services | B12: $150/hr; up to 33 hrs/quarter; $4,950 + $50 overhead | C12: Proposed, not contracted | D12: Accepted written engagement terms | E12: Do not call it contracted | F12: Obtain agreement if accepted
A13: Personal budget / debt | B13: $0 given for each | C13: User-provided | D13: Private budget and lender review if requested | E13: Do not omit requested personal disclosures | F13: Prepare privately
A14: Equipment / operations | B14: No existing KTS essentials reported | C14: User-confirmed | D14: Vendor quotes | E14: Do not present estimates as quotes | F14: Gather 2–3 quotes for major purchases

Sheet WVSBDC Brief
A1: WVSBDC Meeting Brief
A2: One-page working brief for a first counseling conversation.
A4: Business | B4: Kidd’s Technical Services, LLC (KTS), Oak Hill, West Virginia.
A5: Position | B5: Pre-revenue, bootstrapped startup. Starting business cash is $0. KTS has no current contracts, deposits, invoices, purchase orders, or letters of intent.
A6: Initial sale focus | B6: Local-business packages: accurate business information, directions, QR-linked information hubs, local listing cleanup, service-area pages, maps, and care plans.
A7: What exists | B7: Business planning materials covering company, services, market, operations, revenue model, use of funds, financial projections, and agreement framework.
A8: What is requested | B8: Help choosing between staged $25,000 and $50,000 startup funding discussion cases; developing lender-ready monthly forecasts; understanding owner contribution, credit, collateral, documentation, and evidence milestones.
A9: Use of funds | B9: Core setup: legal/professional services, insurance, essential equipment, software/domains/storage/communications, website/portfolio/outreach, limited operating reserve, and project-funded delivery costs.
A10: Cash discipline | B10: Founder pay is $0 in this starter model. Contractor work is project-funded only. Customer deposit policy is modeled at 50% before delivery. ALLIS revenue is $0 and excluded.
A11: Personal context | B11: Founder receives personal caregiver compensation through a Medicaid-waiver program. It is personal income, not KTS revenue. Founder is a caregiver; business operations and financing must be phased realistically around that responsibility.
A12: Questions | B12: What is the smallest responsible funding path? Which program and lender type fit? What owner financial documents, customer validation, cash flow, credit, collateral, and debt-service evidence are needed before applying?
